tp_but_ge2i
