Metadata-Version: 2.2
Name: tp_but_ge2i
Version: 2026.0.2
Summary: An educational package for 3rd year BUT GE2I
Author-email: Didier Larraillet <didier.larraillet@srd-energies.fr>
Classifier: Development Status :: 4 - Beta
Classifier: Intended Audience :: Education
Classifier: License :: OSI Approved :: MIT License
Classifier: Operating System :: OS Independent
Classifier: Programming Language :: Python :: 3.10
Requires-Python: >=3.10
License-File: LICENSE.txt
Requires-Dist: jupyter
Requires-Dist: matplotlib==3.8.3
Requires-Dist: numpy==1.26.4
Requires-Dist: pandapower==2.13.1
Requires-Dist: pandas==2.2.0
Requires-Dist: plotly==5.19.0
Requires-Dist: python-igraph==0.11.4
